[{"path":"/components/forms/tag/children","parentPath":"/components/forms/tag","name":"children","type":"string","kind":"string","mandatory":false,"tags":null,"description":"Content to display in the tag","defaultValue":null,"types":null,"__typename":"Property"},{"path":"/components/forms/tag/disabled","parentPath":"/components/forms/tag","name":"disabled","type":"boolean","kind":"boolean","mandatory":false,"tags":null,"description":"Disables the tag","defaultValue":null,"types":[{"path":"/components/forms/tag/disabled/false","parentPath":"/components/forms/tag/disabled","name":"false","type":"false","kind":"interface","mandatory":false,"tags":null,"description":"","returnType":null,"types":null,"__typename":"Property"},{"path":"/components/forms/tag/disabled/true","parentPath":"/components/forms/tag/disabled","name":"true","type":"true","kind":"interface","mandatory":false,"tags":null,"description":"","returnType":null,"types":null,"__typename":"Property"}],"__typename":"Property"},{"path":"/components/forms/tag/onClick","parentPath":"/components/forms/tag","name":"onClick","type":"() => void","kind":"method","mandatory":false,"tags":null,"description":"Callback when tag is clicked or keypressed","defaultValue":null,"types":null,"__typename":"Property"},{"path":"/components/forms/tag/onRemove","parentPath":"/components/forms/tag","name":"onRemove","type":"() => void","kind":"method","mandatory":false,"tags":null,"description":"Callback when remove button is clicked or keypressed","defaultValue":null,"types":null,"__typename":"Property"}]
